{
  "name" : "SinghalandBrokenKeyboard",
  "testType" : "SINGLE",
  "input" : {
    "type" : "STANDARD",
    "fileName" : "input.txt"
  },
  "output" : {
    "type" : "STANDARD",
    "fileName" : "output.txt"
  },
  "tests" : [ {
    "input" : "4\na\nab\naba\naa\n",
    "output" : "2\n4\n8\n3\n",
    "index" : 0,
    "active" : true
  } ],
  "location" : "src/codeforceString",
  "vmArgs" : "-Xmx256m -Xss64m",
  "mainClass" : "Main",
  "taskClass" : "codeforceString.SinghalandBrokenKeyboard",
  "checkerClass" : "net.egork.chelper.checkers.TokenChecker",
  "checkerParameters" : "",
  "testClasses" : [ ],
  "date" : "2020.06.14",
  "contestName" : "",
  "truncate" : true,
  "inputClass" : "FastIO.InputReader",
  "outputClass" : "FastIO.OutputWriter",
  "includeLocale" : false,
  "failOnOverflow" : false,
  "interactive" : false,
  "interactor" : "net.egork.chelper.tester.Interactor"
}